odoo/addons/purchase_stock_analytic/README.rst
odoo/addons/purchase_stock_analytic/__init__.py
odoo/addons/purchase_stock_analytic/__manifest__.py
odoo/addons/purchase_stock_analytic/i18n/es.po
odoo/addons/purchase_stock_analytic/i18n/it.po
odoo/addons/purchase_stock_analytic/i18n/pt_BR.po
odoo/addons/purchase_stock_analytic/i18n/purchase_stock_analytic.pot
odoo/addons/purchase_stock_analytic/models/__init__.py
odoo/addons/purchase_stock_analytic/models/purchase_order_line.py
odoo/addons/purchase_stock_analytic/readme/DESCRIPTION.md
odoo/addons/purchase_stock_analytic/readme/USAGE.md
odoo/addons/purchase_stock_analytic/static/description/icon.png
odoo/addons/purchase_stock_analytic/static/description/index.html
odoo/addons/purchase_stock_analytic/tests/__init__.py
odoo/addons/purchase_stock_analytic/tests/test_purchase_stock_analytic.py
odoo_addon_purchase_stock_analytic-18.0.1.0.0.2.dist-info/METADATA
odoo_addon_purchase_stock_analytic-18.0.1.0.0.2.dist-info/WHEEL
odoo_addon_purchase_stock_analytic-18.0.1.0.0.2.dist-info/top_level.txt
odoo_addon_purchase_stock_analytic-18.0.1.0.0.2.dist-info/RECORD
