Metadata-Version: 2.1
Name: odoo-addon-purchase_stock_analytic
Version: 18.0.1.0.0.2
Requires-Python: >=3.10
Requires-Dist: odoo-addon-stock_analytic==18.0.*
Requires-Dist: odoo==18.0.*
Summary: Copies the analytic distribution of the purchase order itemto the stock move
Home-page: https://github.com/OCA/account-analytic
License: AGPL-3
Author: ACSONE SA/NV,Odoo Community Association (OCA)
Author-email: support@odoo-community.org
Classifier: Programming Language :: Python
Classifier: Framework :: Odoo
Classifier: Framework :: Odoo :: 18.0
Classifier: License :: OSI Approved :: GNU Affero General Public License v3
